<?xml version='1.0' encoding='utf-8'?>
<Document xmlns="urn:iso:std:iso:20022:tech:xsd:pain.001.001.03"><CstmrCdtTrfInitn><GrpHdr><MsgId>631b0685-4c9e-4579-bfe9-613fb7e5da67</MsgId><CreDtTm>2025-05-29T01:08:39Z</CreDtTm><NbOfTxs>1</NbOfTxs><CtrlSum>10</CtrlSum><InitgPty><Nm>Baroness Anna Meyer</Nm></InitgPty></GrpHdr><PmtInf><PmtInfId>631b0685-4c9e-4579-bfe9-613fb7e5da67</PmtInfId><PmtMtd>TRF</PmtMtd><BtchBookg>false</BtchBookg><NbOfTxs>1</NbOfTxs><CtrlSum>10</CtrlSum><PmtTpInf><SvcLvl><Cd>SEPA</Cd></SvcLvl></PmtTpInf><Dbtr><Nm>Baroness Anna Meyer</Nm><PstlAdr><StrtNm>Frankfurter Allee 11</StrtNm><TwnNm>10247 Berlin</TwnNm><Ctry>DE</Ctry></PstlAdr></Dbtr><DbtrAcct><Id><IBAN>DE00500700100200044824</IBAN></Id></DbtrAcct><CdtTrfTxInf><PmtId><EndToEndId>E2E066cb3e0b85d89117002b3709888a655</EndToEndId><InstrId>7c2afeb39af5c36b1c76873823debe8ec2a</InstrId></PmtId><Amt><InstdAmt Ccy="EUR">10</InstdAmt></Amt><Cdtr><Nm>Tom Winter</Nm><PstlAdr><StrtNm>Augsburger Strasse 14a</StrtNm><TwnNm>80337 München</TwnNm><Ctry>DE</Ctry></PstlAdr></Cdtr><CdtrAcct><Id><IBAN>DE00500700100200044874</IBAN></Id></CdtrAcct><CdtrAgt><FinInstnId><BIC>DEUTDEFFXXX</BIC></FinInstnId></CdtrAgt><RmtInf><Ustrd>Payment Investment</Ustrd></RmtInf></CdtTrfTxInf></PmtInf></CstmrCdtTrfInitn></Document>